serialsrv/__init__.py
serialsrv/__main__.py
serialsrv/serialsrv.json
serialsrv/abap/serial_class_test.abap
serialsrv/abap/serial_service_class.abap
serialsrv-1.0.34.dist-info/licenses/LICENSE
serialsrv-1.0.34.dist-info/METADATA
serialsrv-1.0.34.dist-info/WHEEL
serialsrv-1.0.34.dist-info/entry_points.txt
serialsrv-1.0.34.dist-info/top_level.txt
serialsrv-1.0.34.dist-info/RECORD
