Metadata-Version: 2.4
Name: serialsrv
Version: 1.0.34
Summary: Serial Port Reader HTTP Service with ABAP integration
Home-page: https://github.com/altaykireci/serialsrv
Author: opriori - Altay Kirecci
Author-email: altay.kirecci@gmail.com
Project-URL: Bug Reports, https://github.com/altaykireci/serialsrv/issues
Project-URL: Source, https://github.com/altaykireci/serialsrv
Project-URL: Documentation, https://github.com/altaykireci/serialsrv#readme
Keywords: serial,http,server,abap,sap,iot,arduino,sensor
Classifier: Development Status :: 4 - Beta
Classifier: Intended Audience :: Developers
Classifier: License :: OSI Approved :: MIT License
Classifier: Operating System :: OS Independent
Classifier: Programming Language :: Python :: 3
Classifier: Programming Language :: Python :: 3.7
Classifier: Programming Language :: Python :: 3.8
Classifier: Programming Language :: Python :: 3.9
Classifier: Programming Language :: Python :: 3.10
Classifier: Programming Language :: Python :: 3.11
Classifier: Programming Language :: Python :: 3.12
Classifier: Topic :: Internet :: WWW/HTTP :: HTTP Servers
Classifier: Topic :: Software Development :: Libraries :: Python Modules
Classifier: Topic :: System :: Hardware :: Hardware Drivers
Classifier: Topic :: System :: Networking
Requires-Python: >=3.7
License-File: LICENSE
Requires-Dist: requests>=2.25.0
Requires-Dist: pyserial>=3.5
Dynamic: author
Dynamic: author-email
Dynamic: classifier
Dynamic: description
Dynamic: description-content-type
Dynamic: home-page
Dynamic: keywords
Dynamic: license-file
Dynamic: project-url
Dynamic: requires-dist
Dynamic: requires-python
Dynamic: summary
